<?xml version="1.0" encoding="utf-8" ?><dwsync><file name=".DS_Store" server="sv2122.xserver.jp/plsc.xsrv.jp/public_html/" local="3567141771" remote="3566863680" Dst="-1" /><file name="design.css" server="sv2122.xserver.jp/plsc.xsrv.jp/public_html/" local="3567141775" remote="3566863680" Dst="-1" /><file name="design.scss" server="sv2122.xserver.jp/plsc.xsrv.jp/public_html/" local="3567141772" remote="3566863680" Dst="-1" /><file name="extend.scss" server="sv2122.xserver.jp/plsc.xsrv.jp/public_html/" local="3567141772" remote="3566863680" Dst="-1" /><file name=".DS_Store" server="ktygch.xsrv.jp/ktygch.xsrv.jp/public_html/ec_plusc/wp-content/" local="3567141771" remote="3580792980" Dst="-1" /><file name="design.scss" server="ktygch.xsrv.jp/ktygch.xsrv.jp/public_html/ec_plusc/wp-content/" local="3567141772" remote="3580792980" Dst="-1" /><file name="design.css" server="ktygch.xsrv.jp/ktygch.xsrv.jp/public_html/ec_plusc/wp-content/" local="3580457829" remote="3580792980" Dst="-1" /><file name="extend.css" server="ktygch.xsrv.jp/ktygch.xsrv.jp/public_html/ec_plusc/wp-content/" local="3580457829" remote="3580792980" Dst="-1" /><file name="extend.scss" server="ktygch.xsrv.jp/ktygch.xsrv.jp/public_html/ec_plusc/wp-content/" local="3567141772" remote="3580792980" Dst="-1" /></dwsync>